designer_plugin/__init__.py
designer_plugin/api.py
designer_plugin/designer_plugin.py
designer_plugin/logger.py
designer_plugin/models.py
designer_plugin/py.typed
designer_plugin/d3sdk/__init__.py
designer_plugin/d3sdk/ast_utils.py
designer_plugin/d3sdk/client.py
designer_plugin/d3sdk/function.py
designer_plugin/d3sdk/session.py
designer_plugin-1.2.1.dist-info/licenses/LICENSE
designer_plugin-1.2.1.dist-info/METADATA
designer_plugin-1.2.1.dist-info/WHEEL
designer_plugin-1.2.1.dist-info/top_level.txt
designer_plugin-1.2.1.dist-info/RECORD
