Metadata-Version: 2.4
Name: designer-plugin
Version: 1.2.1
Summary: Python library for creating Disguise Designer plugins with DNS-SD discovery and remote Python execution
Author-email: Tom Whittock <tom.whittock@disguise.one>, Taegyun Ha <taegyun.ha@disguise.one>
License-Expression: MIT
Project-URL: Homepage, https://github.com/disguise-one/python-plugin
Project-URL: Documentation, https://developer.disguise.one/plugins/python-execution-api/
Project-URL: Issues, https://github.com/disguise-one/python-plugin/issues
Project-URL: Sponsor, https://www.disguise.one
Classifier: Programming Language :: Python :: 3
Classifier: Operating System :: OS Independent
Requires-Python: >=3.11
License-File: LICENSE
Requires-Dist: aiohttp>=3.13.2
Requires-Dist: pydantic>=2.12.4
Requires-Dist: requests>=2.32.5
Requires-Dist: types-requests>=2.32.4.20250913
Requires-Dist: zeroconf>=0.39.0
Dynamic: license-file
